dizzydj/Downloader.py
dizzydj/__init__.py
dizzy_dj-0.1.dist-info/LICENSE.txt
dizzy_dj-0.1.dist-info/METADATA
dizzy_dj-0.1.dist-info/WHEEL
dizzy_dj-0.1.dist-info/top_level.txt
dizzy_dj-0.1.dist-info/RECORD
