Metadata-Version: 2.1
Name: dizzy-dj
Version: 0.1
Summary: YouTube video to mp3 converter
Home-page: https://github.com/kaustubh-ai/DizzyDJ
Author: Kaustubh Dixit
Author-email: kaustubh.29.dixit@gmail.com
License: UNKNOWN
Platform: UNKNOWN
Classifier: Programming Language :: Python :: 3
Classifier: License :: OSI Approved :: MIT License
Classifier: Operating System :: OS Independent
Requires-Python: >=3
Requires-Dist: Selenium (>=3)
